{
  "parent": "minecraft:recipes/root",
  "rewards": {
    "recipes": [
      "dragonmounts:water_dragon_scale_bow"
    ]
  },
  "criteria": {
    "has_the_recipe": {
      "trigger": "minecraft:recipe_unlocked",
      "conditions": {
        "recipe": "dragonmounts:water_dragon_scale_bow"
      }
    },
    "has_scales": {
      "trigger": "minecraft:inventory_changed",
      "conditions": {
        "items": [
          {
            "item": "dragonmounts:water_dragon_scales"
          }
        ]
      }
    }
  },
  "requirements": [
    [
      "has_the_recipe",
      "has_scales"
    ]
  ]
}